LICENSE.txt
MANIFEST.in
README.rst
setup.py
django_eggnog.egg-info/PKG-INFO
django_eggnog.egg-info/SOURCES.txt
django_eggnog.egg-info/dependency_links.txt
django_eggnog.egg-info/requires.txt
django_eggnog.egg-info/top_level.txt
django_eggnog.egg-info/zip-safe
eggnog/__init__.py
eggnog/admin.py
eggnog/models.py
eggnog/management/commands/__init__.py
eggnog/management/commands/checkupdates.py
eggnog/migrations/0001_initial.py
eggnog/migrations/__init__.py