Metadata-Version: 1.1
Name: django-eggnog
Version: 0.0.1
Summary: Displays available egg updates from PyPi
Home-page: http://github.org/mridang/django-eggnog
Author: Mridang Agarwalla
Author-email: mridang.agarwalla@gmail.com
License: BSD License
Download-URL: http://github.com/mridang/django-eggnog/downloads
Platform: UNKNOWN
Classifier: Environment :: Web Environment
Classifier: Intended Audience :: Developers
Classifier: License :: OSI Approved :: BSD License
Classifier: Operating System :: OS Independent
Classifier: Programming Language :: Python
Classifier: Framework :: Django
